{
  "content": [
    {
      "content": null,
      "created": "2025-08-17T08:52:29.156228Z",
      "format": null,
      "hash": null,
      "hash_algorithm": null,
      "last_modified": "2025-08-17T08:50:46.823340Z",
      "mimetype": "image/png",
      "name": "plot-parallel-coord.png",
      "path": "slides/images/plot-parallel-coord.png",
      "size": 225611,
      "type": "file",
      "writable": true
    },
    {
      "content": null,
      "created": "2025-08-17T08:52:29.155228Z",
      "format": null,
      "hash": null,
      "hash_algorithm": null,
      "last_modified": "2025-08-17T08:50:46.822340Z",
      "mimetype": "image/png",
      "name": "periodic_features.png",
      "path": "slides/images/periodic_features.png",
      "size": 244572,
      "type": "file",
      "writable": true
    },
    {
      "content": null,
      "created": "2025-08-17T08:52:29.157228Z",
      "format": null,
      "hash": null,
      "hash_algorithm": null,
      "last_modified": "2025-08-17T08:50:46.825340Z",
      "mimetype": "image/png",
      "name": "skrub-table-vectorizer.png",
      "path": "slides/images/skrub-table-vectorizer.png",
      "size": 293206,
      "type": "file",
      "writable": true
    },
    {
      "content": null,
      "created": "2025-08-17T08:52:29.156228Z",
      "format": null,
      "hash": null,
      "hash_algorithm": null,
      "last_modified": "2025-08-17T08:50:46.823340Z",
      "mimetype": "image/png",
      "name": "qr-code.png",
      "path": "slides/images/qr-code.png",
      "size": 14169,
      "type": "file",
      "writable": true
    },
    {
      "content": null,
      "created": "2025-08-17T08:52:29.158228Z",
      "format": null,
      "hash": null,
      "hash_algorithm": null,
      "last_modified": "2025-08-17T08:50:46.825340Z",
      "mimetype": "image/svg+xml",
      "name": "skrub.svg",
      "path": "slides/images/skrub.svg",
      "size": 20787,
      "type": "file",
      "writable": true
    }
  ],
  "created": "2025-08-17T08:52:29.158228Z",
  "format": "json",
  "hash": null,
  "hash_algorithm": null,
  "last_modified": "2025-08-17T08:52:29.158228Z",
  "mimetype": null,
  "name": "images",
  "path": "slides/images",
  "size": null,
  "type": "directory",
  "writable": true
}